README.md
setup.py
kamo_cli.egg-info/PKG-INFO
kamo_cli.egg-info/SOURCES.txt
kamo_cli.egg-info/dependency_links.txt
kamo_cli.egg-info/entry_points.txt
kamo_cli.egg-info/requires.txt
kamo_cli.egg-info/top_level.txt
kamocli/VERSION
kamocli/__init__.py
kamocli/__main__.py
kamocli/utils.py
kamocli/commands/__init__.py
kamocli/commands/auth.py
kamocli/commands/builds.py
kamocli/commands/db.py
kamocli/commands/ed.py
kamocli/commands/jobs.py
kamocli/commands/login.py
kamocli/commands/nodes.py
kamocli/commands/profile.py
kamocli/commands/tenants.py
kamocli/ed/__init__.py
kamocli/ed/kamoplugin.py
kamocli/ed/coreplugins/__init__.py
kamocli/ed/coreplugins/localdev.py
kamosdk/VERSION
kamosdk/__init__.py
kamosdk/config.py
kamosdk/exceptions.py
kamosdk/session.py
kamosdk/utils.py