Metadata-Version: 2.1
Name: kamo-cli
Version: 1.1.5
Summary: Kamo Commandline Tool
Home-page: UNKNOWN
Author: Directive Games
Author-email: info@directivegames.com
License: MIT
Platform: UNKNOWN
Classifier: Intended Audience :: Developers
Classifier: License :: OSI Approved :: MIT License
Classifier: Operating System :: OS Independent
Classifier: Programming Language :: Python :: 3
Requires-Python: >=3.6
